{
"aevilogi":{"deck":["magicscrollsofhiminnsokva","soulfiredemon","fyyronyrthedragon","eternalsunseeker","handofashes","everstonesymbiote","chaosemperor","fierylion","thesilvercrow","felixfyris","empoweringmedicine","magmagolem","largefireball","wizardofeverburn","hydraoftheseas"],"commander":"aevilogi","name":"Ævilogi"},
"skyvisindi":{"deck":["tormentedwarrior", "magicscrollsofhiminnsokva", "skymonkey", "eternalsunseeker", "whisperwindsprite", "blossomsylph", "themythicalpegasus", "mysticalowl", "crystalbat", "tenebrousmage", "theskyboundserpent", "rioocolorido", "tornadospell", "corruptionspell", "voidultraray"],"commander":"skyvisindi","name":"Skývísindi"},
"krakithrek":{"deck":["magicscrollsofhiminnsokva", "captainoctopus", "shiaomasterofseas", "thethousandtoothed", "bulkcherry", "mermaidofterror", "bobtheblobfish", "potionofregeneration", "deepseaspell", "crystalbat", "shokobutsu", "hydraoftheseas", "freezespell", "empoweringmedicine", "vineserpent"],"commander":"krakithrek","name":"Krakiþrek"},
"valkejord":{"deck":["bulkcherry", "wisemysticalgolem", "vineserpent", "potionofregeneration", "themysticalpegasus", "blackholespell", "kratos", "fierylion", "everstonesymbiote", "chaosbrigade", "ferngoat", "blossomsylph", "eternalsunseeker", "skymonkey", "consumedwerewolf"],"commander":"valkejord","name":"Valkejörd"},
"vafisorg":{"deck":["voidultraray", "crystalbat", "chaosemperor", "chaosbrigade", "smokeball", "blackholespell", "kratos", "gargoyleofthevoid", "tormentedwarrior", "handofashes", "thethousandtoothed", "tenebrousmage", "consumedwerewolf", "soulfiredemon", "fierylion"],"commander":"vafisorg","name":"Vafisorg"}
}
